[
    {
        "name": "Толстовка",
        "link": "https://www.wildberries.ru/catalog/21506806/detail.aspx?targetUrl=MI",
        "price": "659 ₽"
    },
    {
        "name": "Брюки для малыша",
        "link": "https://www.wildberries.ru/catalog/29300586/detail.aspx?targetUrl=MI",
        "price": "529 ₽"
    },
    {
        "name": "720 детских влажных салфеток с алоэ и витамином Е, 6 пачек п…",
        "link": "https://www.wildberries.ru/catalog/12073017/detail.aspx?targetUrl=MI",
        "price": "399 ₽"
    },
    {
        "name": "Худи для девочки Толстовка с капюшоном детская Кофта",
        "link": "https://www.wildberries.ru/catalog/45933847/detail.aspx?targetUrl=MI",
        "price": "1 301 ₽"
    },
    {
        "name": "Сандалии LiteRide Stretch Sandal",
        "link": "https://www.wildberries.ru/catalog/10992848/detail.aspx?targetUrl=MI",
        "price": "3 189 ₽"
    },
    {
        "name": "",
        "link": "https://www.wildberries.ru/catalog/19885380/detail.aspx?targetUrl=MI",
        "price": ""
    },
    {
        "name": "",
        "link": "https://www.wildberries.ru/catalog/15398837/detail.aspx?targetUrl=MI",
        "price": ""
    },
    {
        "name": "Худи толстовка для мальчика девочки",
        "link": "https://www.wildberries.ru/catalog/78172298/detail.aspx?targetUrl=MI",
        "price": "3 000 ₽"
    },
    {
        "name": "Масло для загара Ambre Solaire, 200мл",
        "link": "https://www.wildberries.ru/catalog/2915230/detail.aspx?targetUrl=MI",
        "price": "452 ₽"
    },
    {
        "name": "Комплект пинеток и антицарапок",
        "link": "https://www.wildberries.ru/catalog/43802554/detail.aspx?targetUrl=MI",
        "price": "323 ₽"
    },
    {
        "name": "Куртка для новорожденного меховая",
        "link": "https://www.wildberries.ru/catalog/66248404/detail.aspx?targetUrl=MI",
        "price": "1 672 ₽"
    },
    {
        "name": "Антицарапки",
        "link": "https://www.wildberries.ru/catalog/64331266/detail.aspx?targetUrl=MI",
        "price": "352 ₽"
    },
    {
        "name": "",
        "link": "https://www.wildberries.ru/catalog/11066058/detail.aspx?targetUrl=MI",
        "price": ""
    },
    {
        "name": "",
        "link": "https://www.wildberries.ru/catalog/79327866/detail.aspx?targetUrl=MI",
        "price": ""
    },
    {
        "name": "Эликсир многофункциональный 12в1 Эксперт-уход, 200 мл",
        "link": "https://www.wildberries.ru/catalog/6583985/detail.aspx?targetUrl=MI",
        "price": "499 ₽"
    },
    {
        "name": "Детское флисовое худи оверсайз с капюшоном и карманом-кенгур…",
        "link": "https://www.wildberries.ru/catalog/50544542/detail.aspx?targetUrl=MI",
        "price": "894 ₽"
    },
    {
        "name": "Брюки для малыша",
        "link": "https://www.wildberries.ru/catalog/36538416/detail.aspx?targetUrl=MI",
        "price": "730 ₽"
    },
    {
        "name": "Костюм для малыша нательный тройка боди штанишки шапка мишка",
        "link": "https://www.wildberries.ru/catalog/117812740/detail.aspx?targetUrl=MI",
        "price": "1 280 ₽"
    },
    {
        "name": "Худи",
        "link": "https://www.wildberries.ru/catalog/45908491/detail.aspx?targetUrl=MI",
        "price": "1 015 ₽"
    },
    {
        "name": "Весы Mi Smart Scale 2",
        "link": "https://www.wildberries.ru/catalog/9181767/detail.aspx?targetUrl=MI",
        "price": "1 490 ₽"
    },
    {
        "name": "Комбинезон нательный для новорожденного, слип для малышей",
        "link": "https://www.wildberries.ru/catalog/78761236/detail.aspx?targetUrl=MI",
        "price": "630 ₽"
    },
    {
        "name": "Шапка для малыша Набор шапочка, царапки и пинетки для новоро…",
        "link": "https://www.wildberries.ru/catalog/75377329/detail.aspx?targetUrl=MI",
        "price": "260 ₽"
    },
    {
        "name": "Кофта для малыша",
        "link": "https://www.wildberries.ru/catalog/78311959/detail.aspx?targetUrl=MI",
        "price": "2 200 ₽"
    },
    {
        "name": "Свитшот",
        "link": "https://www.wildberries.ru/catalog/62917019/detail.aspx?targetUrl=MI",
        "price": "1 154 ₽"
    },
    {
        "name": "",
        "link": "https://www.wildberries.ru/catalog/61914203/detail.aspx?targetUrl=MI",
        "price": ""
    },
    {
        "name": "",
        "link": "https://www.wildberries.ru/catalog/36911321/detail.aspx?targetUrl=MI",
        "price": ""
    },
    {
        "name": "",
        "link": "https://www.wildberries.ru/catalog/26414401/detail.aspx?targetUrl=MI",
        "price": ""
    },
    {
        "name": "",
        "link": "https://www.wildberries.ru/catalog/17386348/detail.aspx?targetUrl=MI",
        "price": ""
    },
    {
        "name": "Брюки штаны для мальчика для девочки для новорожденных",
        "link": "https://www.wildberries.ru/catalog/52377948/detail.aspx?targetUrl=MI",
        "price": "447 ₽"
    },
    {
        "name": "Крем-спрей для волос 15в1, 250 мл",
        "link": "https://www.wildberries.ru/catalog/6583968/detail.aspx?targetUrl=MI",
        "price": "535 ₽"
    },
    {
        "name": "Костюм для малыша",
        "link": "https://www.wildberries.ru/catalog/76479697/detail.aspx?targetUrl=MI",
        "price": "3 190 ₽"
    },
    {
        "name": "Комплект одежды для новорожденных малышей",
        "link": "https://www.wildberries.ru/catalog/64360397/detail.aspx?targetUrl=MI",
        "price": "1 300 ₽"
    },
    {
        "name": "Комбинезон для новорожденного Тай-Дай",
        "link": "https://www.wildberries.ru/catalog/51191403/detail.aspx?targetUrl=MI",
        "price": "1 489 ₽"
    },
    {
        "name": "",
        "link": "https://www.wildberries.ru/catalog/45385268/detail.aspx?targetUrl=MI",
        "price": ""
    },
    {
        "name": "",
        "link": "https://www.wildberries.ru/catalog/6605334/detail.aspx?targetUrl=MI",
        "price": ""
    },
    {
        "name": "Швабра с отжимом и ведром для мытья пола",
        "link": "https://www.wildberries.ru/catalog/10396483/detail.aspx?targetUrl=MI",
        "price": "1 376 ₽"
    },
    {
        "name": "Телевизор 32F540S 32\" Full HD Smart TV Wi-Fi Bluetooth",
        "link": "https://www.wildberries.ru/catalog/85419059/detail.aspx?targetUrl=MI",
        "price": "14 500 ₽"
    },
    {
        "name": "Пылесос вертикальный Deerma DX700S",
        "link": "https://www.wildberries.ru/catalog/67265142/detail.aspx?targetUrl=MI",
        "price": "3 267 ₽"
    },
    {
        "name": "Худи для новорожденных",
        "link": "https://www.wildberries.ru/catalog/31616039/detail.aspx?targetUrl=MI",
        "price": "909 ₽"
    },
    {
        "name": "Костюм спортивный для малыша из футера",
        "link": "https://www.wildberries.ru/catalog/110374684/detail.aspx?targetUrl=MI",
        "price": "2 056 ₽"
    },
    {
        "name": "Купальник слитный женский",
        "link": "https://www.wildberries.ru/catalog/3454022/detail.aspx?targetUrl=MI",
        "price": "899 ₽"
    },
    {
        "name": "Беспроводные наушники Pro",
        "link": "https://www.wildberries.ru/catalog/36030005/detail.aspx?targetUrl=MI",
        "price": "1 490 ₽"
    },
    {
        "name": "Костюм \"Радость моя\"",
        "link": "https://www.wildberries.ru/catalog/83974872/detail.aspx?targetUrl=MI",
        "price": "465 ₽"
    },
    {
        "name": "Детское молочко 4, 1200г",
        "link": "https://www.wildberries.ru/catalog/15499893/detail.aspx?targetUrl=MI",
        "price": "899 ₽"
    },
    {
        "name": "Робот мойщик окон W100, стеклоочиститель",
        "link": "https://www.wildberries.ru/catalog/13891839/detail.aspx?targetUrl=MI",
        "price": "9 100 ₽"
    },
    {
        "name": "Подушка 50х70, детская, гипоаллергенная",
        "link": "https://www.wildberries.ru/catalog/14747575/detail.aspx?targetUrl=MI",
        "price": "500 ₽"
    },
    {
        "name": "Швабра с отжимом и ведром для дома для мытья окон и полов",
        "link": "https://www.wildberries.ru/catalog/29329709/detail.aspx?targetUrl=MI",
        "price": "2 732 ₽"
    },
    {
        "name": "Вязаный комбинезон новорожденному малышу набор на выписку",
        "link": "https://www.wildberries.ru/catalog/112039309/detail.aspx?targetUrl=MI",
        "price": "1 883 ₽"
    },
    {
        "name": "Подгузники-трусики XL 12-22 кг 50 шт",
        "link": "https://www.wildberries.ru/catalog/4475177/detail.aspx?targetUrl=MI",
        "price": "1 286 ₽"
    },
    {
        "name": "",
        "link": "https://www.wildberries.ru/catalog/34190391/detail.aspx?targetUrl=MI",
        "price": "1 290 ₽"
    },
    {
        "name": "Комбинезон нательный для малыша одежда для маловесных и недо…",
        "link": "https://www.wildberries.ru/catalog/77241726/detail.aspx?targetUrl=MI",
        "price": "804 ₽"
    },
    {
        "name": "Комплект пинеток и антицарапок хлопок",
        "link": "https://www.wildberries.ru/catalog/32847969/detail.aspx?targetUrl=MI",
        "price": "301 ₽"
    },
    {
        "name": "чепчик для новорожденного,одежда для новорожденных,царапки",
        "link": "https://www.wildberries.ru/catalog/56695976/detail.aspx?targetUrl=MI",
        "price": "312 ₽"
    },
    {
        "name": "Толстовка для детей, детская кофта",
        "link": "https://www.wildberries.ru/catalog/77510248/detail.aspx?targetUrl=MI",
        "price": "1 476 ₽"
    },
    {
        "name": "Порошок для стирки и пятновыводитель",
        "link": "https://www.wildberries.ru/catalog/50135343/detail.aspx?targetUrl=MI",
        "price": "499 ₽"
    },
    {
        "name": "Комплект нарядный для малыша в рубчик",
        "link": "https://www.wildberries.ru/catalog/51136067/detail.aspx?targetUrl=MI",
        "price": "1 275 ₽"
    },
    {
        "name": "Топ женский вечерний офисный новогодний базовый под пиджак",
        "link": "https://www.wildberries.ru/catalog/70300966/detail.aspx?targetUrl=MI",
        "price": "778 ₽"
    },
    {
        "name": "Средство для бассейна и быта 10л (11кг)",
        "link": "https://www.wildberries.ru/catalog/81924601/detail.aspx?targetUrl=MI",
        "price": "1 839 ₽"
    },
    {
        "name": "Шампунь и кондиционер для слабых волос",
        "link": "https://www.wildberries.ru/catalog/17575454/detail.aspx?targetUrl=MI",
        "price": "2 366 ₽"
    },
    {
        "name": "Толстовка на молнии для девочки мальчика",
        "link": "https://www.wildberries.ru/catalog/78126942/detail.aspx?targetUrl=MI",
        "price": "1 178 ₽"
    },
    {
        "name": "Комплект одежды на выписку новорожденных",
        "link": "https://www.wildberries.ru/catalog/27412290/detail.aspx?targetUrl=MI",
        "price": "1 504 ₽"
    },
    {
        "name": "Компактный эпилятор с питанием от сети Satinelle Essential B…",
        "link": "https://www.wildberries.ru/catalog/11913257/detail.aspx?targetUrl=MI",
        "price": "5 490 ₽"
    },
    {
        "name": "Комбинезон для малыша Костюм для малыша",
        "link": "https://www.wildberries.ru/catalog/45933453/detail.aspx?targetUrl=MI",
        "price": "1 646 ₽"
    },
    {
        "name": "Велосипедки женские спортивные черные",
        "link": "https://www.wildberries.ru/catalog/21154521/detail.aspx?targetUrl=MI",
        "price": "443 ₽"
    },
    {
        "name": "Гель для стирки универсальный, 5л",
        "link": "https://www.wildberries.ru/catalog/14792613/detail.aspx?targetUrl=MI",
        "price": "959 ₽"
    },
    {
        "name": "Комплект тостовка и брюки",
        "link": "https://www.wildberries.ru/catalog/32285265/detail.aspx?targetUrl=MI",
        "price": "1 063 ₽"
    },
    {
        "name": "Вязаный комбинезон новорожденному малышу набор на выписку",
        "link": "https://www.wildberries.ru/catalog/112039458/detail.aspx?targetUrl=MI",
        "price": "2 152 ₽"
    },
    {
        "name": "Подгузники трусики детские размер 4 L",
        "link": "https://www.wildberries.ru/catalog/16797236/detail.aspx?targetUrl=MI",
        "price": "1 416 ₽"
    },
    {
        "name": "Комплект для малыша, шапочка, распашонка кофточка, ползунки",
        "link": "https://www.wildberries.ru/catalog/70638280/detail.aspx?targetUrl=MI",
        "price": "826 ₽"
    },
    {
        "name": "Теплый зимний вязаный костюм для малыша",
        "link": "https://www.wildberries.ru/catalog/29367144/detail.aspx?targetUrl=MI",
        "price": "3 570 ₽"
    }
]